{
  "indexes": [
    {
      "collectionGroup": "prayerRequests",
      "queryScope": "COLLECTION",
      "fields": [
        {
          "fieldPath": "createdAt",
          "order": "DESCENDING"
        }
      ]
    },
    {
      "collectionGroup": "companions",
      "queryScope": "COLLECTION",
      "fields": [
        {
          "fieldPath": "griefType",
          "order": "ASCENDING"
        },
        {
          "fieldPath": "allowMatching",
          "order": "ASCENDING"
        }
      ]
    },
    {
      "collectionGroup": "companions",
      "queryScope": "COLLECTION",
      "fields": [
        {
          "fieldPath": "griefType",
          "order": "ASCENDING"
        },
        {
          "fieldPath": "griefStage",
          "order": "ASCENDING"
        },
        {
          "fieldPath": "allowMatching",
          "order": "ASCENDING"
        }
      ]
    },
    {
      "collectionGroup": "connectionRequests",
      "queryScope": "COLLECTION",
      "fields": [
        {
          "fieldPath": "toUserId",
          "order": "ASCENDING"
        },
        {
          "fieldPath": "status",
          "order": "ASCENDING"
        },
        {
          "fieldPath": "createdAt",
          "order": "DESCENDING"
        }
      ]
    },
    {
      "collectionGroup": "messages",
      "queryScope": "COLLECTION",
      "fields": [
        {
          "fieldPath": "timestamp",
          "order": "ASCENDING"
        }
      ]
    },
    {
      "collectionGroup": "journals",
      "queryScope": "COLLECTION_GROUP",
      "fields": [
        {
          "fieldPath": "type",
          "order": "ASCENDING"
        },
        {
          "fieldPath": "createdAt",
          "order": "DESCENDING"
        }
      ]
    }
  ],
  "fieldOverrides": []
}